LICENSE
MANIFEST.in
README.rst
setup.py
abi2doc/__init__.py
abi2doc/doc.py
abi2doc/find_attrs.py
abi2doc/join_attrs.py
abi2doc/macros.txt
abi2doc.egg-info/PKG-INFO
abi2doc.egg-info/SOURCES.txt
abi2doc.egg-info/dependency_links.txt
abi2doc.egg-info/entry_points.txt
abi2doc.egg-info/top_level.txt
abi2doc/cocci/get_show_struct.cocci
abi2doc/cocci/match_struct.cocci
abi2doc/cocci/show_store.cocci