Metadata-Version: 1.2
Name: abi2doc
Version: 1.6
Summary: Linux Kernel sysfs attribute documentation generator
Home-page: https://github.com/aishpant/attribute-documentation
Author: Aishwarya Pant
Author-email: aishpant@gmail.com
License: GPLv2
Download-URL: https://github.com/aishpant/attribute-documentation/archive/1.6.tar.gz
Keywords: documentation sysfs linux
Platform: UNKNOWN
Requires-Python: >=3
